{
  "graph:open-local": [
    {
      "modifiers": [
        "Mod",
        "Shift"
      ],
      "key": "G"
    }
  ],
  "workspace:edit-file-title": [
    {
      "modifiers": [],
      "key": "F6"
    }
  ],
  "tag-pane:open": [],
  "editor:insert-callout": [
    {
      "modifiers": [
        "Ctrl"
      ],
      "key": "Q"
    }
  ],
  "editor:insert-link": [
    {
      "modifiers": [
        "Ctrl"
      ],
      "key": "I"
    }
  ],
  "editor:attach-file": [
    {
      "modifiers": [
        "Ctrl"
      ],
      "key": "F"
    }
  ],
  "outline:open-for-current": [],
  "outline:open": [],
  "insert-template": [
    {
      "modifiers": [
        "Ctrl"
      ],
      "key": "T"
    }
  ],
  "editor:insert-embed": [],
  "editor:open-search-replace": [
    {
      "modifiers": [
        "Mod",
        "Alt"
      ],
      "key": "F"
    },
    {
      "modifiers": [
        "Mod"
      ],
      "key": "R"
    }
  ],
  "file-explorer:open": [
    {
      "modifiers": [
        "Ctrl",
        "Shift"
      ],
      "key": "P"
    }
  ],
  "file-explorer:reveal-active-file": [
    {
      "modifiers": [
        "Ctrl"
      ],
      "key": "P"
    }
  ]
}